wzy_dummypkg/__init__.py
wzy_dummypkg-0.1.0.dist-info/LICENSE
wzy_dummypkg-0.1.0.dist-info/METADATA
wzy_dummypkg-0.1.0.dist-info/WHEEL
wzy_dummypkg-0.1.0.dist-info/top_level.txt
wzy_dummypkg-0.1.0.dist-info/RECORD
