Metadata-Version: 2.1
Name: wzy-dummypkg
Version: 0.1.0
Summary: A Python library to calculate dot product
Home-page: https://github.com/Dr-WangZhiyuan/wzy_dummypkg
Author: Dr. Zhiyuan Wang
Author-email: wang1399@e.ntu.edu.sg
License: UNKNOWN
Platform: UNKNOWN
Classifier: Programming Language :: Python :: 3
Classifier: License :: OSI Approved :: MIT License
License-File: LICENSE
Requires-Dist: numpy
